{
    "BHDLIOICLPK": "1190",
    "NHHOLCBCDGJ": "1196",
    "GMLGGJCMJGH": "1189",
    "BKDFGPLGGGB": "1176",
    "BAKKCODKNDD": "1116",
    "AHALAPHDHHM": "1141",
    "MHPFILLGJOJ": "1163",
    "BOGDLGCDJGN": "1159",
    "DCPFIKALCJL": "1178",
    "PMHDPEOJPNM": "1112",
    "PGIFCEKLNPJ": "1165",
    "FNCKPACOKHE": "1199",
    "FLHNPKJFAKG": "1175",
    "CENAHNNLLGI": "1146",
    "PJPCHDNKAEC": "1182",
    "LFMMEIHIAED": "2659",
    "LLBPPPADHLB": "2666",
    "EEADCANEHCK": "2667",
    "HKJFMELKBDM": "2699",
    "MEAKOLJPEIM": "2665",
    "NHNCPAEFMCD": "2676",
    "OOLJMFCIIFF": "2169",
    "NOLJHGCNFBG": "2182",
    "FAJCGNIBCDO": "2044",
    "HCGGECOOAMK": "2187",
    "IBOMHHNFFID": "2172",
    "DMOCPEKHGHA": "2186",
    "OIIEMAPPMNO": "2020",
    "JCHMIGLBFBJ": "2192",
    "IIEIAEEFLGL": "2122",
    "MMDEIBDCLBL": "2108",
    "ODMNCOGPFCG": "2112",
    "BHEFKNOPEOO": "2177",
    "CONHOPDNJDG": "2189",
    "PMKNFFOEOAE": "2032",
    "KPIGNOHEMPD": "2171",
    "HLMACGMHFJK": "2076",
    "GEOLGMFGJMF": "2016",
    "ENENLFCFCKN": "2115",
    "CFJBHLNIJEF": "2153",
    "OLDCBCPCPAL": "2093",
    "NJCLGLANLMO": "2198",
    "BNBOGNHLECH": "2126",
    "EFCJOBBJGOG": "2107",
    "EFONMANINGG": "2124",
    "HGPJLOBEENG": "2165",
    "EIEMLGGBNAI": "2097",
    "PIFPBALEJLO": "2167",
    "DEPBDKOOCIC": "2160",
    "HEHBPMJFELC": "2053",
    "FNHJEINKLFH": "2116",
    "PMAAFMAEHHG": "2120",
    "ANMDGDOAFPG": "2190",
    "FLPBNMKKFKN": "2018",
    "MFDCJHEOKAJ": "2159",
    "PNJBCLJOKMN": "2134",
    "IBFOKKDKNMJ": "2073",
    "EIKKKOKNECG": "2162",
    "LEMFIGECFGI": "2123",
    "HINEJJLGENI": "2010",
    "PIOBLFIEPEK": "2061",
    "HJPEGJLNEKL": "2033",
    "LADELAPFEJE": "2003",
    "ECLCGDCJKBI": "2067",
    "LJGHKOONHHG": "2089",
    "BIAFELBCIEJ": "2127",
    "BGGGHMGMGMB": "2140",
    "JINFBPEOBDM": "2005",
    "GFPCJOCCGMC": "2135",
    "CEBJPNKOOLN": "2007",
    "PJHILCHKKNF": "2094",
    "OLCOEPJPFIL": "2082",
    "CEBNEHCJNOC": "2161",
    "AFLODNHHHJN": "2158",
    "GIOGOPPLLGE": "2188",
    "ECIKJEPKJFL": "2036",
    "KJGLHKCALBL": "2050",
    "EEGMMGOBAGB": "2030",
    "CCFNOMPGAMF": "2118",
    "JNFNNIBKPND": "2156",
    "MGFOFHBEEIE": "2101",
    "CMCJHJPFMFK": "2081",
    "BBBCOOCMJOL": "2075",
    "NEONMHEFOKM": "2194",
    "JCAKGKAECOI": "2180",
    "MOFAIACOJPN": "2151",
    "CKHBPAAGBOH": "2174",
    "LDBCGCPFHNO": "2088",
    "IDBBCLDOHKB": "2042",
    "GKANNBKMMBN": "2039",
    "LKPBOMLAPJJ": "2200",
    "NCLAPAOLOLH": "2099",
    "KJCIKMJNKDL": "2191",
    "KLBOJNGFBLL": "2113",
    "APGOHOIGBMF": "2078",
    "KAKMMNAPDNE": "2009",
    "KDLGEMJLDJK": "2040",
    "KBJNDOHCCIE": "2060",
    "INHEBNAKIKD": "2106",
    "IBCJOBLIEGP": "2117",
    "NDDGJOOBBEK": "2175",
    "IKGEDMDANAK": "2090",
    "OKJDKBOLLBO": "2083",
    "LIFDCBKIHNJ": "2149",
    "MABEFLOHILA": "2168",
    "NHIJDMNKEMF": "2136",
    "POEACIEHMGO": "2074",
    "KAFKKGPKOFM": "2035",
    "COANAEGJOIF": "2041",
    "GPAHEAKOKPL": "2130",
    "MEBLGJIHPBH": "2057",
    "BENODBPGBGP": "2147",
    "LHMBOGKCLGB": "2045",
    "IGGHACDDJHC": "2163",
    "EBOFNEMBJCD": "2121",
    "OHGIACFCBDK": "2164",
    "CNKCMJMFHIP": "2100",
    "DOBNAPMLACB": "2150",
    "PILCGKOELAC": "2063",
    "KOOIIJFMMHJ": "2001",
    "BPMGLBBNAPD": "2103",
    "NKFGJMDKJCJ": "2070",
    "OEOALPJFLGC": "2058",
    "HHHMEFJMNAA": "2080",
    "OHHICPFOJGM": "2133",
    "AEABBBBPHPN": "2199",
    "KFGCJIJPJAI": "2183",
    "MNIEPLELFPA": "2017",
    "OKEJCCLPGCC": "2056",
    "POAEBEADEAG": "2114",
    "MJLIOMCGIHK": "2086",
    "BNDDIBJFHJL": "2091",
    "EHJFDIKIABJ": "2142",
    "LOJGHFIINHP": "2038",
    "NHNCAFGLKGB": "2043",
    "FLKCCEBGKDA": "2055",
    "FNLIIEOFBGI": "2068",
    "NCGCAEBOIGG": "2054",
    "HPBMFFNJHOC": "2144",
    "PKAKPOJAEHN": "2170",
    "EDBGLCIMCLG": "2028",
    "KGKOFKIOHBH": "2125",
    "LDINKLGLFFD": "2021",
    "NLGHNCOBFEL": "2006",
    "LJLOJANKBPD": "2143",
    "GANAMONPBKB": "2110",
    "AOFKHINBNPA": "2132",
    "OJCOGGKJONA": "8687",
    "DDDFAGAJHNH": "8475",
    "ACCDBHIBKJE": "8479",
    "GIMBCMPHMDE": "8925",
    "GFDJDKEGKBB": "8133",
    "FNDBHKAEEBB": "8631",
    "HNCICPPOJLF": "8088",
    "ALALDMAJIKB": "8121",
    "GGLLLDKODNO": "8381",
    "IHEKMDMMNEH": "8068",
    "APIBLPLOAHC": "8052",
    "DLCGFIJKLKF": "8933",
    "MFNPMJKAMNM": "8684",
    "AMFICLCIIOE": "8993",
    "BBNHHOBEHIN": "8283",
    "EHFFBMKBHAA": "8775",
    "GEHFBCEJOOE": "8872",
    "AFMCHCJOMPE": "8339",
    "GFIMONONAEB": "8151",
    "LAMLGINPBCI": "8537",
    "BBDEIOEDMOF": "8943",
    "MGGNIBPAOEK": "8364",
    "GBCDBNEANGC": "8804",
    "MDDHCOPOMLB": "8558",
    "FNALLLKMOKK": "8243",
    "POPPJIDDBDH": "8461",
    "JEBDFCABMKE": "8122",
    "LLHLPMOHHKF": "8030",
    "HAADBMMELOK": "8916",
    "LGDLEIHFKDC": "8201",
    "GFOHFILANIJ": "8835",
    "PHFCPOBGHGO": "8889",
    "DMKCCBFCIBI": "8410",
    "IDPMOCBEPIN": "8583",
    "MDCEJECJBAC": "8636",
    "MLFMNHKIFNK": "8780",
    "MAEIFFICOIC": "8465",
    "KFDFIIMBCPO": "8287",
    "GLEMOHFHHBI": "8506",
    "ACHNGCDDBMA": "8618",
    "GNLNKEJEPIG": "8406",
    "LKIGMBJJGED": "8782",
    "CPINAKDAFBG": "8132",
    "GBBPJPMGIKM": "8511",
    "PJHAOMDBHEJ": "8263",
    "EPJHBBCCCED": "8159",
    "NGDHJCIAKMC": "8599",
    "ANNCMJAEJKA": "8192",
    "HKDMDDFLHND": "8630",
    "DEJPLOKCHLE": "8606",
    "HBHFPDGFOML": "8427",
    "JHIAOLOMKAL": "8849",
    "HCLBPCCIBAL": "8534",
    "PHPDCNJODNE": "8342",
    "DJKEPJOIBMJ": "8628",
    "MECALNNAOKO": "8750",
    "JCKKCIOGMPD": "8444",
    "BFGKDELGOHP": "8722",
    "IBEKENNCOLB": "8409",
    "IDFGDEOPGLI": "8280",
    "POHNNONJGLA": "8047",
    "OFGOIFFGPCI": "8698",
    "EEBADFBJJMD": "8324",
    "OOMIPNMLMFN": "8317",
    "ALNIKBPODLO": "8552",
    "JGBLGANDHDI": "8817",
    "CNGGPGPNJDP": "8584",
    "EILMBOBIDGI": "8741",
    "LFKKACBLNFF": "8997",
    "IDILNEBLNKG": "8520",
    "ANGINIGHGFC": "8447",
    "CNEKANMAICI": "8980",
    "OGAEOJCNIJP": "8853",
    "GHJKGODOFFM": "8646",
    "HGHHBFJOHEF": "8351",
    "JBGDFBKCNFH": "8822",
    "LFCPDAGJKDN": "8663",
    "HOBKGBOCPMM": "8794",
    "BJAJBCMCMGD": "8209",
    "FFKOFNELHNI": "8915",
    "KHFNIEFPEEP": "8809",
    "FJLEGFGIHPO": "8467",
    "PBOEDPIMPEA": "8868",
    "NNJHAPEPALJ": "8043",
    "OFJAFPNOOOH": "8180",
    "LJKKNOCLNGF": "8562",
    "IGAGICLJCLC": "8571",
    "DECMCFHDGFM": "8693",
    "MGJNLCEFLMB": "8239",
    "GDEBDNKNOLK": "8225",
    "MENPBJEIOAG": "8365",
    "CHANIJLEFJA": "8205",
    "JHKLNBALBMH": "8561",
    "KJHIAFBFDDO": "8614",
    "CCBBCBAPIEF": "8210",
    "IJBAJKMEMJN": "8456",
    "ABHJCBPOEFC": "8250",
    "IEAGNJHMKHB": "8104",
    "EIPMPMPMJPE": "8639",
    "MBMDCDCICHF": "8379",
    "HKPCJMACGEA": "8512",
    "DIFCABEKCFF": "8156",
    "ABFDFANIJEK": "8292",
    "NKACBDDGFOO": "8128",
    "HLHFHLBHOMB": "8034",
    "GKGFGLOKGDM": "8270",
    "MKEALAHEINH": "8702",
    "CGNGOIAICCF": "8844",
    "FPJDOJOCALO": "8062",
    "DPELCNHJHDF": "8423",
    "FJJAIHHLNMC": "8546",
    "DNGOLEEEPKM": "8597",
    "BBLLCOADDPM": "8307",
    "AHLJANOBIMN": "8163",
    "NPOLMCJJCKP": "8674",
    "FHPIDHMKKPM": "8436",
    "HGEHGJECBJC": "8968",
    "HLEIPNANFJF": "8438",
    "OAJDBCPAIFJ": "8945",
    "LBOAGFOKOHL": "8215",
    "OOHKNAIKHNK": "8451",
    "PNBCNMLOAIF": "8803",
    "GIJMALACHPC": "8271",
    "CFIOFNGIDPJ": "8253",
    "MLLGAPAALPB": "8563",
    "PHCBDIDADFJ": "8255",
    "AOHCNKLIHDD": "8971",
    "LOFMGIDPBIK": "8015",
    "DHAJNMCJGHD": "8732",
    "GGBDLMCILGE": "8495",
    "FLLCEDEPHHB": "8385",
    "GAHJJDLCPKI": "8229",
    "BCNIMOKNOOJ": "8236",
    "HDGLOCPPIII": "8596",
    "LMCEGNAPGKE": "8203",
    "OIIOGDNIDGK": "8340",
    "LNGLOPJLLNH": "8677",
    "AACAGBIGNIK": "8649",
    "MCJCCFLDBHK": "8165",
    "LDJMIBJJIIG": "8578",
    "CJFFCHLKFMD": "8604",
    "DPPNCLMMMMB": "8363",
    "FGJFOEGNDIN": "8496",
    "EGKMBIHKJOB": "8729",
    "DPBDKEPJDIJ": "8839",
    "ADLEHEJPCKE": "8593",
    "NNLIGIGADKL": "8322",
    "LBPDMFCCNDF": "8473",
    "IBCLLIIOPEE": "8576",
    "IMMAPONENCG": "8545",
    "FEFNCKMDIDB": "8312",
    "GEGEEILHMJI": "8966",
    "LMPKBIBCGNA": "8761",
    "DEABICNFMEE": "8673",
    "ECJGNLPFACF": "8579",
    "NPOCMDBFHNC": "8415",
    "JIGIEEIOHCF": "8598",
    "PKKNKADEAGP": "8013",
    "EJHNOAFBMKF": "8651",
    "BFFJAMBLFHI": "8869",
    "BLFOENGGJAK": "8875",
    "JPIOJPILOCF": "8018",
    "LFECJIBHEPN": "8357",
    "IAMGMPONLOL": "8440",
    "GLAIMPCKKHB": "8446",
    "IMMLFIOGPAJ": "8328",
    "KBAAIPKAPHE": "8852",
    "NHABBBDGKCI": "8483",
    "GKEAJMEAECN": "8029",
    "PAMMFIELIDA": "8442",
    "BBCEMDKAKBJ": "8113",
    "BLJKLGOEANF": "8140",
    "HLMGLPKCHGE": "8648",
    "LLGLJCIIHNO": "8430",
    "HBKDABDOFEG": "8859",
    "GEOJJNICOPJ": "8586",
    "PAJKHOIGBFG": "8262",
    "ENFGOPAEPBM": "8393",
    "OJLIHHCOEKD": "8459",
    "AOKKFEIGDIC": "8086",
    "NEEPOMKBDAK": "8712",
    "NMKALJIDENA": "8327",
    "ICGPFMFGHNF": "8152",
    "EFDEDAPCBKP": "8055",
    "EFOFHAJFPDA": "8360",
    "IANAFMKHBFE": "8613",
    "IOLEDMPEMMP": "8524",
    "OGAHNLAGKPI": "8252",
    "EBBJOPBNHDB": "8126",
    "LNPAAPEMOMK": "8503",
    "JHPGPCBHJIB": "8958",
    "MCCOAEMCDDM": "8348",
    "GINOCLNKMLI": "8724",
    "PIDFKFDDNOJ": "8155",
    "MDHINEKBGGN": "8213",
    "AOKLAJLBEPJ": "8275",
    "HHLJCILFCFJ": "8120",
    "OLMKGCCALAM": "8856",
    "JDDBNBOGBAK": "8354",
    "LKJPJBKJAAA": "8928",
    "EGKKBFLBJNE": "8411",
    "JCLHEAKGHLO": "8807",
    "CEMGCKDHCEC": "8178",
    "CNGKIJFLPJM": "8053",
    "PKFMIJJIEJG": "8079",
    "HOAFHAEHDLJ": "8555",
    "IGMLBCPGBAL": "8462",
    "OHNHLABOCHA": "8191",
    "NCFOMHIINBL": "8245",
    "LEKAFPACHHK": "8160",
    "ANAGINKCDEH": "8082",
    "BLGBAPGBLAC": "8139",
    "OMGGPDKPDCH": "8616",
    "GCAAKGBBFNK": "8531",
    "MIBGIHLGKIE": "8535",
    "GDMAJNCEDPO": "8006",
    "IOBHIJKKHJM": "8432",
    "JHFJJDBBOON": "8214",
    "HIIAOANGENE": "8061",
    "PBDKPEIHGGA": "8797",
    "JFCHJNHIHOO": "8021",
    "KKNEENJMFHL": "8051",
    "FHOFEALEPBE": "8836",
    "ELNAIHBNPKN": "8147",
    "IEEAGCKDJAA": "8671",
    "AIOCOPNMCBL": "8796",
    "LHENIEHBMFB": "8014",
    "CJIMIGKPIFG": "8110",
    "LGDKJAHMFCH": "8525",
    "LEFMHBANNII": "8543",
    "DNAEJFJFPPA": "8272",
    "EBEBCGBHJKH": "8846",
    "EIHJCAKIHND": "8269",
    "DLADJEHJDPB": "8536",
    "MDEBIBMKAFM": "8403",
    "KGOHJODOKGD": "8145",
    "EFPHPEGLJGN": "8513",
    "HFIDECGGIGF": "8764",
    "FHBKALGPONC": "8602",
    "MOKDJJEKNOJ": "8587",
    "CPJIKPCPOJO": "8237",
    "NEDABGEDHJO": "8095",
    "LDOBABFHGNE": "8347",
    "ANCNBCHBNIL": "8867",
    "MKEDLCFFAOO": "8944",
    "FNFJECFFMIG": "8387",
    "GHACIAABHBJ": "8825",
    "HCPCIFCJGFE": "8540",
    "OIADJFNAMII": "8769",
    "EAPDFFJGMOE": "8910",
    "HGIEPCDKBPA": "8466",
    "FEGOKDNDBCO": "8650",
    "IPCDEJHFGNO": "8995",
    "LEDKBLPLFGB": "8424",
    "PGHAGBMLCDD": "8010",
    "JKPJHJGEJHJ": "8056",
    "MINCIEAHAPO": "8260",
    "CLNICKOLOIM": "8754",
    "GIFOKLMMPJA": "8577",
    "FEOHDNPHBJI": "8390",
    "DFECEAOCJLI": "8138",
    "PGOHFGDLCFG": "8644",
    "LFCEEOOPGEN": "8864",
    "GLBPOJCMBPK": "8982",
    "GMNFLKICICI": "8931",
    "GEBHCHEKCBD": "8572",
    "OLNMIFOCKHO": "8199",
    "GLBJKAJLDGJ": "8682",
    "CDPNINHBBHF": "8739",
    "KMNMBAGFKAL": "8789",
    "KMPCKELIJKP": "8714",
    "FFGCOLAAELE": "8314",
    "EKOIAIBMIOH": "8273",
    "EILNIKEFBEA": "8311",
    "NKEJJNIMABJ": "8843",
    "MDGJAHGAHBJ": "8876",
    "KNELBIOPMIO": "8715",
    "GPMNIOOFGBD": "8707",
    "PPPAJFNOPEP": "8922",
    "CGJDLLEICGJ": "8811",
    "LGELAEHOADH": "8158",
    "MDMOILDADKG": "8977",
    "CKOMFPDNHBN": "8806",
    "FOACMIDMKCF": "8615",
    "IPNMNIOOKMA": "8091",
    "KKBAAPEFNPG": "8244",
    "HIOCGNACCIK": "8590",
    "IMGFKJFHKFN": "8004",
    "CGOAHGFGKFA": "8594",
    "JDEOJJKFHGI": "8939",
    "HIGNILPNKNO": "8921",
    "BGJBLCDKIND": "8429",
    "HFHGNLCCCMO": "8391",
    "KCFIMDHNONF": "8073",
    "FNJHPEKAFEF": "8785",
    "NHBMLPLOLIE": "8884",
    "PNGLJFIIBEM": "8256",
    "GHCEKHCNJMF": "8710",
    "BFKDOGGBPKO": "8084",
    "HOPOGICCIKF": "8665",
    "APKFMOIFONL": "8609",
    "JBGKJFBFDJO": "8882",
    "FPLHPBAPILH": "8402",
    "KGMDCMKPGOM": "8967",
    "GDDMMCHGDKM": "8516",
    "ECKCANDJMHM": "8096",
    "GGJLNGDHBEJ": "8162",
    "DPGPIGLIIMK": "8927",
    "BKOBKABFOLG": "8990",
    "KGGPJOOPDAI": "8973",
    "DFHOIMLGIHI": "8083",
    "PEIMEBJOKPD": "8005",
    "FEHMLLJEMEM": "8313",
    "CEPDNEKPAOC": "8688",
    "JEMHCOBPNJO": "8965",
    "IDMOIJINDIJ": "8494",
    "HGDDHKIEBLA": "8230",
    "BENODGEDFLD": "8267",
    "LPELNPAHDLO": "8848",
    "GJOELDEPLKK": "8290",
    "KIKFPKCFJMK": "8959",
    "GDJPGPOHGHP": "8770",
    "GILKPCIKPEM": "8841",
    "FJHPNFIKKKA": "8366",
    "PDNJLMHKDIL": "8947",
    "IJDLKKOLKFP": "8629",
    "DIHNGAOLEIB": "8514",
    "BNCCEGKEJLK": "8802",
    "AALBIADOICE": "8141",
    "PIHAIJJOLII": "8697",
    "DNEDBABLMLJ": "8064",
    "DAADLBJHMNF": "8112",
    "ABOMCJNPOPL": "8265",
    "HJCGKJEFBMD": "8166",
    "BEHCDONNJNP": "21749",
    "PJGKPIDAKOJ": "24658",
    "OHGEMJKDCIH": "20410",
    "IDBMLIJNLFC": "22172",
    "CAHLCOBAAOA": "21164",
    "LAIDADNBLKG": "20870",
    "KNFDNMCBKNA": "20091",
    "NLAPJFCGHJL": "20007",
    "ANEBLLGNBIO": "22295",
    "OAELCOKBFKH": "24786",
    "KGICBHFOMMF": "21853",
    "CPEODACPOJJ": "20494",
    "NMOHOIIFAEH": "24050",
    "KNKBOAHFHGE": "24702",
    "BOCHPKJIPPD": "23232",
    "BGCKGNLMJHH": "21852",
    "IPOBJJLKFIC": "24631",
    "APJFDJLFMOI": "21466",
    "GCDEEJOFANE": "22439",
    "AHFKONEEGAK": "21869",
    "OEIFAIJFCEP": "20469",
    "GPIBHNNMOOA": "24758",
    "EBDCHKFCCEB": "24092",
    "GHBOPPMLEEA": "23497",
    "LJPLMCEJECG": "22028",
    "FCAIALHCIKL": "21252",
    "CNOPNEPFGHG": "24826",
    "MFOICNBNHLP": "20591",
    "JGLJENGADON": "20024",
    "JNAFAHLOJLG": "24974",
    "JCHILFKMGON": "21870",
    "GDNPMKGKFBH": "21132",
    "BMLFFNKJLAK": "23287",
    "BGPMNHLOLAE": "21251",
    "NKHKFPKDMOK": "21795",
    "BKAMPLBFEJC": "22707",
    "GFEGGLGCPIB": "24566",
    "CJAAHHNHHGM": "23825",
    "DDJFJCOCPIF": "20581",
    "IFOGABNMJAE": "23197",
    "LPPDJEDKFII": "20722",
    "PAOBGMEJMNI": "24058",
    "JEMJHGJJECK": "24980",
    "IAJAEHMLMAP": "24731",
    "EIMNGGAEPGL": "22355",
    "DEMMHAIDKNK": "21832",
    "PGJFHOOLDEE": "21144",
    "MHEDKPGDENI": "24767",
    "BONNIDICNDJ": "20166",
    "DHPHLFEODEE": "20862",
    "HLCKFFIFGPF": "22742",
    "IPANFPMDLDD": "23012",
    "KDHECBHECKJ": "21265",
    "EIJDIBHELFI": "20229",
    "INPJHOENKHP": "24388",
    "CMABLDADPDH": "24165",
    "JPIAPNHEEOI": "24538",
    "DOPOAKNJCEF": "24841",
    "HICCNJAEIDF": "20488",
    "IDBMONNNPAN": "24171",
    "CBGMOHGHNHC": "24284",
    "JDDDFIOGOFO": "24684",
    "PBOPMKIDBCL": "22893",
    "KFNDOGGBBJH": "24534",
    "JPILDPAFDFP": "23177",
    "KJDACKBICEC": "20353",
    "GDKNNJKAGHF": "23230",
    "NHGJBMKPOJH": "24555",
    "JDNDNFFHCDL": "22163",
    "MGEPGOKKALB": "21230",
    "OGAHKFHDLIE": "22475",
    "OBECOGIBJBH": "23001",
    "IHGNKCPJCPO": "20487",
    "IGHLKGJNJBD": "20704",
    "BOGKEHNLPAM": "22447",
    "MJHDJBKCMAJ": "20224",
    "BOJPIOKKKAA": "23269",
    "ACOJPFKLCJM": "21201",
    "IGIIFOABMFE": "23878",
    "BFGKDKIPBFO": "21076",
    "NOCCAPABBCK": "23071",
    "CADKOIHGKML": "21526",
    "CAHNKALBCBM": "22894",
    "BFLBHJDMNIK": "20761",
    "EDMCDCINNDL": "20946",
    "IDNIDNOCAOO": "24928",
    "LDAMKEBHPEO": "23760",
    "BFHPCEGBKJO": "23686",
    "FMOLJCKDEDF": "22436",
    "OGCGDGMDGEF": "22442",
    "BNMCJLNLNCG": "20710",
    "NEBJBHBFLAK": "23912",
    "NFPGNMEAADP": "23543",
    "NDONAALBHAG": "20576",
    "BBPLDBJJDKK": "20183",
    "KHKDJCPMIMD": "20789",
    "AJELBAPILIK": "24962",
    "BMKCOGGPBBP": "24937",
    "BPJCDHGDCPI": "21647",
    "FBKJHEPOMCM": "21829",
    "HPEDLAPJCCH": "23884",
    "HEGHNPKLDKD": "24780",
    "BNHNLMJHABA": "24530",
    "LOKOMDJJILM": "21977",
    "LLELAFKLNBK": "21089",
    "DCEPABGKBIA": "20602",
    "EJEMJIOGCOF": "24182",
    "MKEADPCANGA": "24992",
    "MHJHENLEPEC": "24118",
    "FNDLCLGFFIO": "20841",
    "MCAGOHGNOLF": "20675",
    "MADBIGEEADF": "23047",
    "GNNNBJPAJNP": "20283",
    "PGOFLLNHMHB": "24158",
    "LOMGKIHPBEO": "21299",
    "OMFGFEMGCPM": "23886",
    "PBMPCFIBGNM": "24969",
    "CGDEMGEBHDA": "20812",
    "KKBBOOBCAMO": "23202",
    "LFFLGJEOHFM": "20618",
    "AFIPONEFADI": "23127",
    "HPEMAPPDFAH": "24776",
    "HAIGODNCPKE": "22574",
    "BNNMGNNFFOG": "24252",
    "NMLBCCPGHPF": "21698",
    "MPBPNIEHNJH": "20385",
    "FHMODKAEMDI": "22209",
    "CHNBHNMMJKC": "20950",
    "IFLFCDPABPB": "24527",
    "ODJNBPIOAOK": "21962",
    "JIOMNFBEAPF": "24485",
    "DCOFHBJNMEG": "22079",
    "CDMLPLHIINJ": "22075",
    "HNHDBOANHDF": "21624",
    "ACEPHCGAPCJ": "21598",
    "DKKHNGCHJHL": "23435",
    "KABDOKKOMBB": "24656",
    "LOEFLAFGOOH": "22438",
    "GIBKMHEKPDN": "24308",
    "HBHJGEIKJEP": "21035",
    "EHJMPKIGAFP": "22145",
    "MDBHGIIOPKI": "20143",
    "OFJKMJFMLCO": "20508",
    "PGHDNINMDJM": "24347",
    "GIIHGMKANHL": "22187",
    "BMBJFJNIAKL": "22180",
    "OKNMFKCKJGP": "20858",
    "JMBNLGPPMDP": "24764",
    "EJLEHCFOMPK": "21504",
    "OHAGCADDFGA": "21758",
    "BFICMJMHKJL": "23293",
    "FLNMFCNPKEH": "23172",
    "CEMGDGAHDPJ": "24935",
    "HCCDEDBNNLH": "21126",
    "PIIMBAGDDNJ": "22162",
    "KHJBEOHBNBG": "23597",
    "AMFIEDJGLPA": "23014",
    "KKEAGOHBCMA": "22846",
    "HNMGHDHJJMF": "21621",
    "EMMNAJMFCBC": "24818",
    "CJEDPJPHDFD": "21417",
    "MMBGBMHBIBA": "23464",
    "MMPGFBFANOB": "22907",
    "MGEHIFOHGIA": "24781",
    "BCMJEDNDIGM": "21475",
    "HNBJBLPCGIK": "24470",
    "OLCOENGMPPC": "24985",
    "DIOKGLJIAMG": "23859",
    "CELPBGOAJJB": "22763",
    "JDPJGAHPGFH": "20071",
    "AKIFJCCDNEM": "22017",
    "NOEABFFFIBJ": "23303",
    "FAPDLKNEPCH": "20550",
    "CNEDGHOJKNH": "20910",
    "LIDDFAKFGLG": "20158",
    "IBEBIDMINKK": "21605",
    "FFEBPGAHDIE": "21778",
    "ENKAIAJHBOL": "23718",
    "JLFLCCDNNIL": "22940",
    "ANLPPAMFPKC": "24529",
    "JFDELDDOOIJ": "20509",
    "PEEKHLNIGJH": "21486",
    "AJFDAKKHGKO": "24951",
    "LGLHGBPEOGD": "20971",
    "PIGIPONAOCL": "23193",
    "MFEOLMIMPCE": "22376",
    "DDHHEKPMCJA": "24406",
    "LIDABDAPMJK": "22570",
    "ODCPBFFABNO": "21648",
    "CMGBHAALJIJ": "22877",
    "DECAIBABCPP": "23245",
    "DCJEGFPGKEF": "24889",
    "NNOJLDPDPIE": "21876",
    "LBFHEDFPGMI": "22710",
    "GELGLOAKDBI": "21051",
    "PMBAFLIIPEC": "20539",
    "IFMDOEMIPDM": "21525",
    "HPJKJMBIFPH": "24533",
    "HMOBMGADFAJ": "23343",
    "DNKBHCGAALL": "21932",
    "DOFGFCEODEN": "21801",
    "IFOKONFKCDP": "24495",
    "FMOMGOBBJAJ": "6359",
    "EEHLGKBAOJJ": "6366",
    "LMCBPKGNHCG": "6392",
    "CMPBNBNBBBL": "6386",
    "JEPIBBDBODC": "1688",
    "MBEFPBGHKGB": "1642",
    "AJELMNOHEPB": "1639",
    "NJDKABDEHGE": "1800",
    "LCBAAKNNLKF": "1699",
    "FKFJKOEDCHL": "1791",
    "BAODCDAOMBM": "1713",
    "LOGCABMLHCM": "1678",
    "BMOIDOOEEFB": "1609",
    "FNOLNFIPFMH": "1640",
    "KLHPMOOFDCO": "1660",
    "DEPMHNALOJG": "1706",
    "BIEIPKNLGIC": "1755",
    "LCJDCDGGAKG": "1705",
    "HPAKJFDBBOJ": "1797",
    "JDMOIGGFIIE": "1778",
    "GGHGIEBOJLC": "1704",
    "AGJOJDPCHDG": "1651",
    "BHCBIKNNPFO": "1666",
    "GIICPGMGBHC": "1738",
    "KMCIHDKBABI": "1717",
    "BBLHLAFMPOK": "1634",
    "EJLLFPAADDN": "1695",
    "DFPOHBMCMAG": "1775",
    "BOMGBIMAENG": "1690",
    "BFEGBKILMIB": "1683",
    "MBNHDAMLHMP": "1749",
    "OGDFANFAIDP": "1768",
    "LIPKPFIMKEG": "1736",
    "BNPGCGPLPOB": "1672",
    "BPDOOALCEFI": "1614",
    "AAHBAHOLAEF": "1623",
    "HCJFKLALPGP": "1698",
    "BNKEDNIIKNJ": "1776",
    "HAGAEOHPAKD": "1613",
    "EFGGOOHEKAE": "1754",
    "MJFGNJJDJDN": "1646",
    "NKALLDNFGAO": "1696",
    "LLALFDHLFJG": "1674",
    "CBILECHOPDD": "1635",
    "GJABBIPEEMJ": "1641",
    "PLLLFENOGLH": "1730",
    "OAPGCKKFJOB": "1657",
    "MMEGEOONABP": "1747",
    "ICFBBMJLJLA": "1645",
    "FMBNPHNEMJA": "1763",
    "JEOOOPFMNOK": "1721",
    "EJAJCEIMPGO": "1764",
    "JLLHOHBNJPM": "1700",
    "BDPJACNADDJ": "1750",
    "FNGICMEGFEL": "1663",
    "BBKJCNMLLCD": "1601",
    "BBALEACLEJE": "1703",
    "JKKNIONOFPI": "1665",
    "GLDBIGJJKPE": "1602",
    "BKHJBJLCGII": "1728",
    "GALLHCNNOGL": "1685",
    "LFPGAJJEPPA": "1649",
    "JGCLHIODNGH": "1670",
    "AFDHKHAFKNE": "1658",
    "BHDFBGFEGPC": "1680",
    "DGFKLHLAFEN": "1733",
    "BBFCJICAALL": "1799",
    "AGIMMGIIAEO": "1783",
    "EEABKLIGNJJ": "1617",
    "HMEJDLEHHGF": "1656",
    "IIBEEMFEJHJ": "1714",
    "CGPNDMOBAOI": "1686",
    "KHDJKFCMPKM": "2609",
    "KOOPEIGFOEN": "2616",
    "PPDFLNOGDEB": "2617",
    "NEBFLGBEDBM": "2649",
    "HBHGGMBOHDP": "2615",
    "HHIAHDBAEBB": "2626",
    "NOFBIGOHAKF": "2645",
    "GPFFNOACEFD": "2622",
    "FDMEHNBNHEO": "2620",
    "APOOMOPLHGB": "2623",
    "KJKIDBGCDHH": "2631",
    "OICCIEGKGFL": "2621",
    "DCGIKJPBKGI": "2650",
    "KABEBBFHLDC": "2624",
    "AKCACDJBBJM": "2625",
    "ENHLMPMFMBG": "2790",
    "JOMNNMGBCCP": "2796",
    "PIGNHADKHPI": "2789",
    "KNJBHGLAELN": "2776",
    "GCPJBEOOFLA": "2716",
    "NGMKEEFBKHD": "2756",
    "DPNNEFOLOFD": "2741",
    "GJDPKMJKHAF": "5040",
    "JBJMMPEKFJA": "5046",
    "OLMKKFNGGEK": "5039",
    "IIHMACNLDCN": "5006",
    "FAKALDAMEDD": "4991",
    "NCFBCDPLLIG": "5022",
    "IGDEALHCKMC": "5042",
    "AFMNLNAKKBN": "5013",
    "HIPHCOIDFEP": "5009",
    "LIEEOGAEGEA": "5028",
    "LNMDKMAKDPA": "4962",
    "IEBBBLDIPCC": "5015",
    "CBJPMIKGFLK": "5049",
    "DEOFNLAMNKE": "4202",
    "CAEKJKGCKLD": "4209",
    "NBJNBHODKPN": "4203",
    "GEEINFDPFHF": "4208",
    "HEELPLADHOF": "4201",
    "IPKAMNDGCKJ": "4206",
    "FIONMEBLJNI": "4205",
    "PHBKIOKCEFL": "4207",
    "JHBLHOOJBKF": "1959",
    "AOBNNHLBNCJ": "1966",
    "PDJGPFHOHPJ": "1967",
    "CEOEONAEPPI": "1999",
    "LNCMJEHKBCI": "1965",
    "FAPCCOFIPHK": "1976",
    "GDPLHDAPLJI": "1995",
    "NDCJPJIIHNC": "1972",
    "NNKBLEKCIDM": "1970",
    "LBGPJMCOBAG": "1973",
    "IKBPJFMCGCP": "1992",
    "FHDOFENPBOB": "1986",
    "MMAKIBIBFJF": "1981",
    "LIBMCEMPILH": "1971",
    "AMPMNKIKBID": "2000",
    "CIGPGHKJCDH": "1974",
    "PDCHAMCAMOB": "1975",
    "GAEFHAOBOLH": "1993",
    "IHHECPLMBEO": "1987",
    "ACJGGIPDPDP": "1998",
    "PJHJLJHPCAP": "1962",
    "HJKFPFCKJAO": "1969",
    "NCAEGBLIDHA": "1994",
    "IFLJBALCLEO": "1968",
    "IJBNDNHGKKH": "1997",
    "AOBLCPCFAPG": "1953",
    "LKHCBDGLADP": "6209",
    "NOLHMPAAHCB": "6216",
    "DDNIDJFDJNO": "6217",
    "HHGCOBLMHEL": "6249",
    "CEKGHJHOGNE": "6222",
    "ECKNBLFINEN": "6220",
    "ABKMBPBDLIE": "6223",
    "MFCCCJJBOJD": "6242",
    "MNMBGJCIKDF": "6236",
    "APIBJAAJMAJ": "6231",
    "BBINENEFGJC": "6221",
    "BABOMHHDDBN": "6250",
    "JMGEODECHIO": "6224",
    "IJODGPEEEEF": "6225",
    "CLLHCDIDKAK": "6243",
    "KHIIOPLDKKF": "6237",
    "HMDPFFCIFCD": "6248",
    "HKBPEFKLLFI": "6212",
    "LLCCAGBHIEJ": "6219",
    "NJMOGCHIHLC": "6244",
    "HMJIKPCPAKA": "6218",
    "CHBKOGGNCPK": "6247",
    "MHIHAJPLCOC": "6203",
    "PPHIDLPEDEG": "6232",
    "ANLCNPLLCCH": "6230",
    "GMBBIGCDKCN": "6201",
    "KOLPPEMABAB": "6246",
    "DAHJKHDDMBP": "6207",
    "GDJDDMOALHA": "6208",
    "IKEAMPBDILA": "6241",
    "FEDBCANJJGD": "6213",
    "OPKAJPENFCI": "6211",
    "GEJLLHOIIOG": "6240",
    "NDPCFBBMFEF": "6234",
    "ALLHKMHKPJC": "6206",
    "HHKLOLJJHGP": "6238",
    "EPHAEALIPIJ": "5489",
    "JPOBFNGODMI": "5476",
    "KAGODPFFHCG": "5416",
    "LNHGNIBIDBK": "5456",
    "PBDACOIIJCI": "5441",
    "AJEOBLEDMDL": "5472",
    "GNBEGCCEKHA": "5492",
    "NJPHDDAINAK": "5463",
    "PPIENGDHNGO": "5459",
    "AMNHIJMNKKC": "5478",
    "FLHLCBJEEFM": "5412",
    "PAFCKKCJDCF": "5465",
    "HDLLHMGLKOB": "990",
    "NJOCOAEINCL": "996",
    "CJLIPEPDAHP": "989",
    "JPNMIFILGBP": "976",
    "DGNGJHAIIEK": "916",
    "FHGNGPJDCIJ": "956",
    "CPLBEGFODJM": "941",
    "MJBBKGDBNJF": "972",
    "CDEOCFMPMKK": "992",
    "ACFCCAJPEOP": "963",
    "GPMGFINNFNA": "959",
    "MMLHGEBMPLF": "978",
    "FKHLCMCPIGC": "912",
    "DPEAFCEFGCN": "965",
    "HAFIIFADEGO": "999",
    "IEIGFGMPFHG": "975",
    "CNIHHPPGEMM": "946",
    "LOAONEMKGFB": "982",
    "DHLGODFFBFB": "942",
    "HBLHJCEKECI": "994",
    "HJENIFKEHEG": "977",
    "ICJOIPMPDGN": "986",
    "BPLIBLDAAJK": "951",
    "NFMELNBDDAE": "939",
    "DFHKBHEIOBF": "995",
    "LDNDCBIJLBK": "950",
    "GAKNPPDEMAH": "948",
    "MCFDHLDDMDA": "998",
    "DODGENPMJPF": "997",
    "NLENKNENICD": "981",
    "GGCLDEAGDEL": "970",
    "IEFAELAKCAL": "935",
    "IKKEGFKLLKB": "933",
    "CMFCCIDLGBI": "983",
    "LHOODIGKDCF": "906",
    "OIECMKEMLLB": "904",
    "DNNABLHCJOK": "954",
    "FGPAKHMHGDN": "943",
    "KEJPKPKPGLD": "929",
    "BKMLEDPDPGP": "928",
    "KBHOKIKGICJ": "974",
    "HPAGGBIOCGI": "973",
    "HJADKLKFJAB": "988",
    "NLLGPPBKJJJ": "949",
    "PILGJINNHNA": "918",
    "BMGILOEIPPD": "958",
    "GIJPAOFHLHB": "915",
    "JDNBAICODLN": "926",
    "KOIONEDIPOO": "940",
    "HCHBPFPMAJC": "945",
    "IOIMANCOPNL": "934",
    "JCGBHBPHHLG": "964",
    "BIDBJCMBNDI": "1000",
    "GPOPDGDIKKP": "957",
    "PFIMOOHJIHL": "937",
    "IOJGGLKDBNN": "924",
    "GCLPINLGBJH": "901",
    "CGKBAPDFIFP": "969",
    "MIILCHAPFCJ": "932",
    "MKLPCGDLALI": "919",
    "MCMBEAGPLJA": "927",
    "AOEICADFFIJ": "968",
    "HOJHJGGEABM": "993",
    "ONHPIKEFGMA": "390",
    "IOKHKCLAMIO": "396",
    "NPBLKELHECA": "389",
    "NIFOOGCHCHM": "376",
    "FJHPBLOMBHI": "316",
    "BAHHBFKIGHP": "356",
    "CDAPHBDGAJH": "341",
    "KBNHHFJKOBM": "372",
    "KDJNEMFCJPK": "392",
    "GAENMKLBNCE": "363",
    "KEMOOLMMMCH": "359",
    "AEMCOFMKGBP": "378",
    "HGBEDNJLLOD": "312",
    "HNLEDDICDGF": "365",
    "EPNEBFCAMBJ": "399",
    "NELLCKEHONH": "386",
    "CDBHOGIJIEF": "351",
    "GBBNPOEHLGD": "339",
    "EHAFMAJCOEJ": "395",
    "JLADAPJELAE": "350",
    "OOLMIAMAJEL": "348",
    "BKNFJDOGHFA": "398",
    "PGOGJAJLDBM": "397",
    "ABEAMHFKNML": "381",
    "FPBBGCJGPON": "335",
    "JDCLEDBBEAH": "333",
    "PBGHFFIDFKC": "383",
    "HNAIHFDMNOD": "306",
    "MLOBPCAHFAJ": "304",
    "AODDNJBLCKM": "354",
    "LJELJMOKMEJ": "374",
    "HKNJGMEMBOD": "373",
    "PCCMPICFEFA": "388",
    "ELKGGPAONOB": "349",
    "JADJLNMNODG": "318",
    "HLNHMNHJPBB": "358",
    "LIPALCJGCFM": "315",
    "GDCDGDCNMLB": "326",
    "LLAEAGCDEND": "340",
    "CPPOJNOOJKB": "345",
    "DPDLNPHNOME": "334",
    "NICHDLMHIME": "364",
    "HAPKANDAINI": "400",
    "BOKDCFPDBFM": "357",
    "ECIGOAGHFLJ": "337",
    "CFIGJLCCPGP": "324",
    "KKCDBAMICJC": "301",
    "AMHAGIPKAMI": "369",
    "HMMIAOJNLAE": "332",
    "GKLAGIKJCAO": "319",
    "LJPOOGNPDNM": "327",
    "AAELEBEPLGM": "368",
    "EEJMACFIBIG": "5809",
    "AOCJAIBECJN": "5816",
    "NCJBDCHGKCH": "5817",
    "BCCAFNMNICP": "5849",
    "JCGJAPODEHI": "5815",
    "ONFJLHLBGOB": "5826",
    "GMOFHIOFJLN": "5845",
    "JNCACPJKIEH": "5822",
    "IAAAOJJEEJG": "5820",
    "MNEBPDHDDLM": "5823",
    "CELGNPCLDDF": "5842",
    "OOHDMAHCFMH": "5836",
    "EGHHKBCHAML": "5831",
    "IKIGLFPJABI": "5821",
    "HNALCFIKNLO": "5850",
    "HBKIHDOHPPE": "5824",
    "ONHGECDIBAM": "5825",
    "CMBCAMNGNBD": "5843",
    "LODNMOGMOOM": "5837",
    "BJGKEKGIPCA": "5848",
    "AMHKOMFJCKN": "1590",
    "BIKLLFLGCCA": "1596",
    "PCNKFCOOMOH": "1589",
    "BIMBGHFINGO": "1576",
    "JEOLICDPLML": "1516",
    "AEEFJKOLIKC": "1556",
    "EHEPDPEIEHP": "1541",
    "BDINGDMDDAL": "1572",
    "LEKKBIGCOGI": "1592",
    "CEEALLJALGP": "890",
    "NMBFBOFBOHD": "896",
    "IFJKFEAFEKJ": "889",
    "JABPJDGCCLD": "876",
    "DBPJFAJEEPK": "816",
    "FFILEPACBBO": "856",
    "OHBOCHMIMFN": "841",
    "CBECLHIKOKP": "872",
    "PMINDIMMDBM": "892",
    "LENHBBMIOJP": "863",
    "CMGHDEALCOM": "859",
    "KLFAKEJGKFK": "878",
    "AELKPGENHOH": "812",
    "GDJHBFGHBOK": "865",
    "NAJCCPACDGD": "899",
    "CDKIHLKOFKJ": "875",
    "CLJJEIKNDFO": "846",
    "PJLEOOFMGND": "882",
    "HDPNKEHBOFA": "842",
    "EBLKPECLKJD": "894",
    "JDHIIDNHDIA": "877",
    "HGDEDCKBIIN": "886",
    "MLIFJHEHJIC": "851",
    "EMIMBIBNOKI": "839",
    "LHOBJJPEFGM": "895",
    "FJFOPOKDAMN": "850",
    "BBGCJHDIJHK": "848",
    "DBEMAIELIGP": "898",
    "DCIIDBFJNMH": "897",
    "MEJCOJFINIL": "881",
    "HBGMHEGICBP": "870",
    "PPKCBCCKLMC": "835",
    "FCKNLPLIOAM": "833",
    "BDHMGDBGLCA": "883",
    "NJBBECLNJOP": "806",
    "CDNLKOIGGDG": "804",
    "PAKGHHLFBMK": "854",
    "EMNIKEJHFDC": "843",
    "LDMCFCEHKJH": "829",
    "LALCHNFNKNF": "5590",
    "KKPPMPIMCKI": "5596",
    "OOMEGDEJPJC": "5589",
    "KAIOAAMLAIM": "5576",
    "JGEBAOBIIFH": "5516",
    "LFHBKCENMLC": "5556",
    "KBFBPCDBDFC": "5541",
    "LOBJFGDKFMP": "5572",
    "IFAFDELBEKM": "5592",
    "PFCCJFBBDKL": "5563",
    "HONDAHLHCKH": "5559",
    "PNAJMJIOAGH": "5578",
    "PACDOEEJGMF": "5512",
    "IEGHEIHGAMM": "5565",
    "EKPFAAFNGJE": "5599",
    "MCDAMGDNAMF": "5575",
    "IFLLIJKABHC": "5546",
    "CCEHPMIELPE": "5582",
    "NHJPMAEBGHN": "5542",
    "ICAJCEJKAEI": "5594",
    "IKHEGGGJEPN": "5577",
    "MGNIILLEFFB": "5586",
    "GCEFCLGFGPE": "5551",
    "KJMLBAHFNHL": "5539",
    "OBGAHIOLAPL": "5595",
    "NHJCFFPDGHB": "5550",
    "MHLFJAIKKMK": "5548",
    "DKCKCIPOEKA": "5598",
    "BONOCJHIGAL": "5597",
    "MHCLLFDBFAC": "5581",
    "JIALODJKPJP": "5570",
    "PBGIAMLDCGI": "5535",
    "GDGGNKEMCOA": "5533",
    "NLMGCGCNKHG": "5583",
    "BCAOAGGPONH": "5506",
    "HDHPLGOCHCP": "5504",
    "ONMECJLKJJC": "5554",
    "MDHPLAGPINN": "5543",
    "EKIOINEMBPA": "5529",
    "FBJAPCKJFCA": "5528",
    "NOOGKCGHOPN": "5574",
    "LMHHDFLHLMN": "7479",
    "AEMOAMOBAEB": "7925",
    "JCMIBMOKICD": "7133",
    "HKNPELGCKEK": "7631",
    "ACPDBCOLLIM": "7088",
    "JKLHNBADGCE": "7068",
    "GADMMILBJOK": "7052",
    "HCNLDKBCBAM": "7933",
    "CCCHPDLEDMO": "7684",
    "PKMOJBOIHAD": "7993",
    "MDPIPCADNIN": "7283",
    "LCDMONCCJOG": "7775",
    "EGNIHJPKBKP": "7872",
    "NAHAENAHEDO": "7339",
    "DDJEPFINJOJ": "7151",
    "ONJMNAJIIHE": "7537",
    "NGBAMCGDDDK": "7943",
    "BOLJIMLDKKL": "7364",
    "JEHMOJKEODL": "7804",
    "CMELIOKBBAM": "7558",
    "CJPDFDFACHM": "7243",
    "LENFGKOMHLI": "7975",
    "BPLAIDOBNMG": "7526",
    "OJDIFIEOINF": "7820",
    "FDCMPHIBAKC": "7035",
    "NKFLEOEPOKD": "7865",
    "JKOODGPGFIC": "7498",
    "KBIOBGNGHKC": "7050",
    "LNELFKCMGNP": "7879",
    "OMDLPLDHBHC": "7367",
    "HADLPGOAPCE": "7303",
    "HGBOBJMKKPF": "7735",
    "MKPDDCLLPOF": "7007",
    "KIPCLAPGJDA": "7117",
    "GMOLCIIJJOD": "7118",
    "BMGDLELMDOL": "7065",
    "ECHBOAOGKHN": "7752",
    "CLIBJPLOGDC": "7037",
    "DKOFLAIPMHK": "7449",
    "IMOCMGPFFLJ": "7398",
    "FAGHNCIAALG": "7176",
    "LMLBLFPAGIK": "7511",
    "HFLGOKMJKEI": "7263",
    "MEIHMKNEJPJ": "7159",
    "CPPJDDNMEJM": "7599",
    "PIEMILPJLAL": "7814",
    "GCLCDECEPJN": "7930",
    "FHLIADHHNAF": "7793",
    "JNMOJGGBJCK": "7507",
    "FBEBHPMGAFJ": "7926",
    "OGJOCAINDFA": "7994",
    "DIAAKFMAGEI": "7414",
    "OAKJEBNHJKG": "7281",
    "CDJPPGINGNH": "7198",
    "OPKHNAMFACE": "7470",
    "ILDNNMNCLJM": "7787",
    "HCCBAHJAGIG": "7332",
    "PMMLAIDANPP": "7407",
    "BACAGPCHJEJ": "7464",
    "IKJMJIFLCAF": "7450",
    "IAJNPJMBICP": "7374",
    "BDPPKOHGFGE": "7107",
    "CHJINHIHBKC": "7179",
    "DGBKNJINFHE": "7605",
    "KEGFDAJCPIO": "7880",
    "EAAHMIEAONL": "7504",
    "EBJCCHCOBNI": "7670",
    "IEPGADDEOLK": "7369",
    "HEDBOGHMAEH": "7510",
    "FLLPOCFFHIA": "7706",
    "IMOLJDDINMH": "7356",
    "MCFHDKFAKEL": "7722",
    "MJLFJPCIPKH": "7111",
    "LMGOHPBHHFN": "7547",
    "NNAAFMMAGIF": "7763",
    "LNCHADCLDFO": "7747",
    "IBOJKHAFLJN": "7949",
    "HLHJMEAHDBG": "7020",
    "EDEMNOENLJO": "7023",
    "MFDDLCKFKBA": "7969",
    "LCKKLLBIMKF": "7766",
    "DGEJKCHBLLK": "7570",
    "AJEAGJAFJOO": "7377",
    "DOBDAICHFII": "7520",
    "LGDLKBJBEOE": "7310",
    "GEBNMMPJMPG": "7920",
    "AFPBCMBHGNC": "7031",
    "MHIGNIDFIJO": "7500",
    "MILOEMBOIBJ": "7988",
    "INJOAAKAIKI": "7274",
    "NMPEGOIHHIH": "7486",
    "CAPOJBJBBPA": "7308",
    "ICCLMODGOGJ": "7669",
    "IKJBDPHEAAD": "7433",
    "ELNEFCODBGJ": "5759",
    "IPDDOLGPOCE": "5766",
    "ONDIOIKGEPL": "5767",
    "DJBBFDIDMLK": "5799",
    "NLPPFFGOIED": "5765",
    "DGDDKAFONCL": "5666",
    "LOFBJHDKDDA": "5659",
    "NKAFABCJHNC": "5667",
    "ECGIAPGNHCG": "5699",
    "LLAFOBGFDIA": "5665",
    "MBLNFDMHCMM": "4504",
    "HNCNJCDKMDL": "4744",
    "NCEADPGPAAD": "4611",
    "MIOECHKEPDH": "4705",
    "GPLCKBLHPND": "4858",
    "IIHAAPIDLAD": "4727",
    "AIJMGMMBCIH": "4879",
    "NCADHAEALEL": "4701",
    "HGMKGBJHFBC": "4587",
    "OOEKDEHCHAE": "4516",
    "PAAMBEAFLAG": "4593",
    "NMPEOOGOBKE": "4822",
    "OIACCGHPIPD": "4461",
    "CECACCENJCG": "4888",
    "NMNPBCABMIB": "4814",
    "BFAIAEEOADP": "4617",
    "JNOPMAOIKHJ": "4621",
    "HDEMDCMNGBA": "4548",
    "POPCEJAJKCN": "4549",
    "JKCNIEJDJEA": "4591",
    "KDEHLHJBMIG": "4725",
    "DJEBHJDBGDL": "4832",
    "EHCFNNNFKNA": "4844",
    "KFFGIGOAKJA": "4518",
    "DDAGFKEEADB": "4457",
    "LIHDMMPLEFA": "4834",
    "NHKAPMNLCOF": "4660",
    "LBMOFLDAOOG": "4873",
    "AKGCBCCDOIP": "4649",
    "OEFHBCCGOAH": "4632",
    "ILKBNHAABKN": "4771",
    "BFJMCDIOHJH": "4896",
    "ELBAMHIEJLG": "4605",
    "BFMLANHPHHK": "4562",
    "ECPIDCALIPC": "4857",
    "KNFIIIHNHHK": "4503",
    "KNKAEPEBGNN": "4757",
    "MLAGPADBHDI": "4845",
    "MILAOMEDEKI": "4746",
    "CHPBONNJCNN": "4631",
    "FFPLCCEFMAP": "4745",
    "EPNIBIGFPOK": "4876",
    "EJCDPKLEJEP": "4501",
    "ILKGKNKEFIP": "4551",
    "KCKLCFKEGLC": "4820",
    "LBIGJHDPPMH": "4669",
    "CLLEAGFNBFB": "4470",
    "GENNEGEOHCD": "4794",
    "HECKGLMELIB": "4897",
    "ACCOBPBFHPH": "4490",
    "GONDOHFJCLK": "4892",
    "MFGDMJPMPBD": "4769",
    "AFJECFFIJCH": "4680",
    "HMKKANIOIKL": "4812",
    "JKKONKOOANK": "4709",
    "AIOIBJHEPKI": "4710",
    "CAAEENHGNLG": "4753",
    "AFJNICPBLBF": "4793",
    "CHBMNPCAJND": "4465",
    "GHCLAJCOLDE": "4826",
    "BEJNPDHEGDO": "4853",
    "GCEOMBOEIEP": "4881",
    "OMHKOHKMPMJ": "4690",
    "EDBKNPNNLMH": "4567",
    "FFBBMLGCDNB": "4634",
    "IPEEBIFNEBD": "4511",
    "DOFAGDOJLAN": "4731",
    "JCKDHCAPEIA": "4825",
    "BDNIDPNDIOH": "4515",
    "MGMPBINMKJG": "4597",
    "AMGABHMJHCA": "4867",
    "AFFCNECKBGG": "4823",
    "GJGLKOMDLJP": "4751",
    "KOKKGGFLIGL": "4687",
    "NBBFEOCBBNF": "4694",
    "JBMNKOKPABK": "4672",
    "FKKOJDOMLBE": "4577",
    "NBELLMAHLCJ": "4519",
    "FOILFLGLJNI": "4768",
    "HACMAFACMPM": "4522",
    "HGGGONGOAHF": "4628",
    "ILDBHFKHBCD": "4626",
    "HMCHAGIMODO": "4788",
    "GKMMANJBFDO": "4565",
    "PEGPLPFJABM": "4464",
    "GEAGFNHCNKB": "4776",
    "FNNJNPLMGCA": "4647",
    "CAAJEDJCBLJ": "4713",
    "JPDELFGIDNG": "4638",
    "JLLBLAEKEEF": "4686",
    "PJJKDAGEDFE": "4533",
    "MPIIBDEPHOI": "4662",
    "AKJFJDIFEBH": "4613",
    "IGHDJPCKECO": "4536",
    "EPFNLONCBBP": "4624",
    "OICPIIMFLHD": "4479",
    "PBIIDNAPDBH": "4476",
    "FPCJFDGHEEL": "4570",
    "COBLKMLHLLP": "4852",
    "KCDKLLPCCPC": "4612",
    "BFNLKGFGGMM": "4600",
    "KPOMBGHCCIJ": "4604",
    "FMABBJFJENA": "4681",
    "IKALBFGKDJD": "4741",
    "MHHDJIJBFIJ": "4807",
    "GMEHKLCHNOO": "4775",
    "OJFNGPIEJDO": "4882",
    "DAGEAJJKJJD": "4889",
    "GBDPEGGNNON": "4764",
    "EBFKBLPDION": "4777",
    "IJFFHALDHCG": "4800",
    "ADFFMDPPKPC": "4851",
    "DOOMGCGOIBA": "4510",
    "GBLIAKFBPFI": "4550",
    "ECKDBAFOHGM": "4755",
    "BFCFMHNMOPJ": "4683",
    "DOIDMHNBLBH": "4836",
    "ONHGONEFGDM": "4543",
    "APPIAPLKDKO": "4840",
    "CILDCMDNIAL": "4756",
    "FNPPMBFAEJP": "4594",
    "INKJFHLNBMB": "4582",
    "KIDOKDPNMAF": "4527",
    "IJEHPPNGEMD": "4782",
    "PHKCFKKMHAF": "4606",
    "AILOGCEEAEF": "4791",
    "EJOHEBEFPID": "4708",
    "HGKMIEPCCCJ": "4480",
    "JFBCACPLFLB": "4883",
    "FGOLIGGOLFH": "4644",
    "KDDLCDFOJLM": "4790",
    "JOPGJDMPLDN": "4781",
    "MMMMGLECHGB": "4785",
    "HPDDMIDMECO": "4469",
    "LKHKEOHFNAA": "4547",
    "KHKDGIEFOAO": "4849",
    "BNDPLOEOLGM": "4609",
    "OCBALMKCPIA": "4841",
    "FEGMIBFFPAB": "4590",
    "BIIGHBNLEOI": "4806",
    "DJHCBMFGKHK": "4553",
    "FEKGILBDFCN": "4737",
    "FPIIONNKFOD": "4894",
    "PAACGBOEJBK": "4720",
    "JMBIGNLPDEC": "4697",
    "AKEHHECCPOO": "4809",
    "FKKDNFEPMIL": "4614",
    "LDAKAIIPNGI": "4833",
    "EGBCJEGNFBG": "4870",
    "APAEMKIJPBM": "4489",
    "ADMHOKGPIHC": "4517",
    "BHLINONJPIP": "4715",
    "IPHKIKKEHJM": "4887",
    "FCKKBJLFDIA": "4309",
    "KFHFEKNDOAL": "4316",
    "GPDDMIAPDMG": "4317",
    "LGMBGPKIBJM": "4349",
    "IIIDHHIHDHN": "4315",
    "ABOAHDLKLFL": "4326",
    "CKGLOBELCOC": "4345",
    "HCNJNLNNNCM": "4322",
    "AJKKNGAPJAH": "4320",
    "NEHHLOADCIO": "4323",
    "PHLJPGECOOA": "4342",
    "FDIOOFPLJBA": "4336",
    "JHEACIJKAJD": "4331",
    "OGILGEHKJIG": "4321",
    "AAGKEHNFPPN": "1917",
    "LHPFEHGIOIP": "1907",
    "BHNOHDDKCNG": "1915",
    "ALBAFICCGIB": "1911",
    "IHKDFEAHNJI": "1930",
    "ICAJDFEAEHE": "1909",
    "ACFFIBPINDH": "1922",
    "HGGBKEKBGJG": "1910",
    "LKMFLLAFCCF": "1927",
    "OHBGMLPFMDD": "1924",
    "NMMIMIJIBKK": "1912",
    "GPFNDHHGNBK": "1918",
    "MJMBGMCPANO": "1904",
    "NFFEDBEJOIE": "690",
    "NMCECMHCPGB": "696",
    "KAMNCMHFHKA": "689",
    "JCKKGBHHMKE": "676",
    "IBLPBENLBJI": "616",
    "BDMPGIOBPKD": "672",
    "FLHLJEFBEDE": "692",
    "PCBLPPLABOH": "663",
    "HHKNLLGKPOO": "659",
    "PPKJGBEEIGE": "665",
    "NBCHEBBHLLC": "699",
    "OEBALMOAHFM": "675",
    "JDGBIPPFOBN": "646",
    "ANIOAPMNCML": "682",
    "AMBOFKCBNMI": "642",
    "AMLFPANDAFE": "694",
    "KANJNJOOJNO": "677",
    "AGLHKLJCGPJ": "686",
    "LKOLNMJMDCE": "651",
    "NNBKFFLOCOE": "639",
    "LCEDADIFDHE": "695",
    "APPALGKPALK": "650",
    "KIPFBEGHHLN": "648",
    "PACEBKOHMDJ": "698",
    "BKACBGIOAIJ": "697",
    "HBJJPKDAMFA": "681",
    "BODKGGEKPHH": "670",
    "IPAGBGMDOJL": "635",
    "EFOOFNIDNMC": "633",
    "BJKEDKMONBM": "683",
    "GFKHDFNBKIC": "606",
    "EHCLDJBNPPB": "604",
    "FDJBLFOADKF": "654",
    "NDJNIINPNCE": "643",
    "MINLPCIDJLK": "629",
    "CLDDOEALBCJ": "628",
    "MOLNIGGHJHE": "674",
    "MJAFJIOFNFE": "673",
    "LFGMKMAGMCE": "688",
    "EFDHMIEGAJA": "640",
    "MAMGPDIODOE": "645",
    "DMMFDIDGIIO": "634",
    "BOFCLLGHIDM": "664",
    "KMDPAEENPIK": "700",
    "DJEPBIENMFA": "657",
    "GPEJPBJAFHM": "637",
    "JMPCEHHBLGI": "624",
    "FEGEABDMGFO": "601",
    "DCKDKJNEPCN": "669",
    "EFAIJMEIALJ": "632",
    "BHEPNMICMKA": "619",
    "ENAGFOOLFAD": "627",
    "NEPCOPEDHAI": "668",
    "KIDBDAJPICA": "693",
    "MIBIHEGKELM": "652",
    "GIMLJCFLMLA": "644",
    "BKJBIOIIJNB": "622",
    "GLJHANJIAPK": "691",
    "GGFMFJKHFOP": "647",
    "OBLLFNIAALA": "636",
    "JDPJOAOAIMC": "638",
    "BJEJIEHPOPH": "660",
    "FJKADHAFOIM": "680",
    "GMNMJNNKPMO": "653",
    "HHKJBJMFJDH": "605",
    "NHMPDGGMDNN": "1496",
    "HHLOLKGJCHP": "1489",
    "IFBKCKFGICP": "1476",
    "HJJCDLCPACH": "1416",
    "MJOIAKOLBNB": "1456",
    "PFLOBKKCCIA": "1441",
    "LGMOLHBKPBD": "1472",
    "NFCEPLAAPBE": "1492",
    "MLDDJLANDPE": "1463",
    "OMGMJPFOPFD": "1459",
    "LBGKJBDFGKP": "1478",
    "GODOJLFLCGL": "1412",
    "GNHCOJIHAOF": "1465",
    "GOLFMOPNENJ": "1499",
    "NPDMPGMDBAL": "4159",
    "CCGNHDDBACB": "4166",
    "FPLLGKLDBDH": "4167",
    "HANOAJKNHPA": "4199",
    "GIGMEAMFOJF": "4165",
    "KOFDGOHGOHH": "4176",
    "JAEBMMNHIFH": "4195",
    "EIOHIEKLPLD": "4172",
    "JFFMEIKNAAL": "4170",
    "HAALJFOCDMI": "4173",
    "APIPBBJHNFE": "4192",
    "ALBACDHHNHN": "4186",
    "MMJGJFFKNII": "4181",
    "HOBHBPEFHDL": "4171",
    "OPDAOPFFNFE": "4200",
    "OFJCIFKHBDL": "4174",
    "EACOAPHAKOH": "4175",
    "GFBABCMFPOH": "4193",
    "BLMCHAALMDP": "4187",
    "PHFEMFDEIPP": "4198",
    "HCLBGOABODC": "3990",
    "CIHBDJAJHLN": "3996",
    "AMGLLIPIOLJ": "3989",
    "EKHNMCNAMGN": "3976",
    "DCCPJAHHMHC": "3916",
    "PNOIFAIDBDL": "3956",
    "PJJDGNBPCIO": "3941",
    "CHIANHIJGEP": "3972",
    "ONLHKPHEIHA": "3992",
    "IFKPKMPHDFD": "3963",
    "EJLGLJHLKMG": "3959",
    "NBHGJELAONN": "3978",
    "EDGNEMFHMBM": "3999",
    "CHDLLDCFKDO": "3975",
    "NDABEMEEAOE": "5209",
    "PPHEBGDHOPA": "5216",
    "ADEJEPJMMLB": "5217",
    "LEEDPLNIJHN": "5249",
    "GMJLNNNOOAB": "5215",
    "OKIOCBFIBFG": "5226",
    "PEAEKOIGBCH": "5245",
    "LFFBMNEPNBG": "5222",
    "NIEOBKOODAE": "5220",
    "AOJDBMGLDFL": "90",
    "BBHCADGJLBK": "96",
    "CNFJJJAIKNB": "89",
    "OOCFBKKPCBC": "76",
    "NKKDDNNONMB": "16",
    "INDGLMIDHBB": "56",
    "DHENDNHBLNA": "72",
    "ACBHFLGOADD": "92",
    "FDLANFBPBIO": "63",
    "MGKNBEFLFIP": "59",
    "EBLBKMMAKNH": "78",
    "LAJIBNCFOMI": "65",
    "IEJMFHELPOE": "99",
    "HOFJCCFFMBO": "75",
    "NMIMOKPBFOI": "46",
    "MOHMOIHPLNM": "82",
    "PDFOAPHCLGI": "42",
    "OEODMJEEKPM": "94",
    "NDMJPBGJMPF": "77",
    "OGEKEHAKECF": "86",
    "GFOBEJIPOED": "39",
    "IAIJFDMCGJI": "51",
    "OMDLGOHPJAD": "95",
    "FPKILDGANHL": "50",
    "AIGHBMDCCOF": "48",
    "EMLFCPLHMPE": "1390",
    "GKDKFFFMCEH": "1809",
    "CFEAALDHMJI": "1816",
    "DCGHCNJEHBH": "1817",
    "MHEHKPFJIPH": "1849",
    "BAFPJDIIFJN": "1815",
    "EINDMHKENJA": "1826",
    "EMOGNCHGMJA": "1845",
    "HMGLDIEKKKD": "1822",
    "COFKBEGFJNB": "1820",
    "IGADDHNAECL": "1823",
    "DEGIPACCNOF": "1842",
    "KDCFGNKNGGB": "1836",
    "CCBPPMJBDGE": "1831",
    "IFCMJCBNEIP": "1821",
    "HPMAFEGNKGP": "1850",
    "NGHOBFHEIMD": "1824",
    "JBCLIDOMFGE": "1825",
    "KGBGGHNFNAN": "1843",
    "FMMKBGLPLCL": "1837",
    "LPMOPIKCHMH": "1848",
    "GAMPLDEBIJM": "1812",
    "GKDMNMMGFPD": "1819",
    "HMKBEINOGKB": "1844",
    "OFKFMCLINLB": "1818",
    "LJPJJCMCKAB": "1847",
    "PACDNJBIANA": "1803",
    "BKKMADOGNHI": "5390",
    "EBPGPLPPIJE": "5396",
    "AKILAOGLLOH": "5316",
    "KJIADCBLEHL": "5356",
    "CJPJGDMCBME": "5341",
    "BMIOKGNEAMJ": "5372",
    "LEPEPBLADCN": "5392",
    "FDIHNNPDDOH": "5363",
    "MOKKBHCLKCA": "5359",
    "MOIDNBFLGOC": "5378",
    "GODFCCHJCLO": "5312",
    "FBEOAMCGJKF": "5365",
    "GDAKADDOIJC": "5399",
    "MIICNJBEKFM": "5375",
    "GKHKOEMINHA": "5371",
    "OLCCMOHCBBP": "5355",
    "DGFAKOLALKC": "5366",
    "LDJKHIMCNAE": "5374",
    "GMHIAPBGKEA": "5373",
    "CFOMJMIBAMH": "5388",
    "NNODMPCAPFC": "5349",
    "EAMGJMJEFPN": "5318",
    "KOJOIEGCFPE": "5358",
    "IJINBICPPIL": "5315",
    "CKGALBJACEN": "5326",
    "HCJEOAOHGDK": "5340",
    "NMAGLFPGECM": "5345",
    "DJBLFOONPMJ": "5327",
    "NIHAFBFKGMP": "5368",
    "FHECKHLMMGC": "5393",
    "PMLLMBCOKOP": "5352",
    "OFJEHEHMPII": "5344",
    "MIGBJBJFKHN": "5322",
    "GOKHLCOPCOJ": "5307",
    "HFGLJAONKGB": "5391",
    "MOHONANDFPN": "5347",
    "ANMKBBNIEJF": "5336",
    "JEHKOCCOBLN": "5338",
    "GNALOFPIHJC": "5360",
    "FGKBEPBLMMD": "5317",
    "ELLGJMJANOH": "5320",
    "PJMKIDEOBFM": "5385",
    "GMCIJDCJFGD": "5331",
    "CPGONBLCMEM": "5325",
    "JKOPOEHPAOM": "5367",
    "DCCMKDBMIOL": "5379",
    "NLIDOGHJPCM": "5313",
    "FJECLMPCGAP": "5387",
    "OICAJMKMEMJ": "5362",
    "FKNFKDBHFDM": "5323",
    "EPLLEJADMPA": "5330",
    "GNCOBJFHHNG": "6569",
    "OIOFGAJIDIH": "6598",
    "BFFEMLKIMGD": "6497",
    "BACLCEEBIAD": "6461",
    "LPCLBLKFNPB": "590",
    "BFJDBEKGICD": "596",
    "DBFOHJIIGPF": "576",
    "DCJOFPGCGPJ": "516",
    "ECHDOLNIDMO": "556",
    "JDLKAEHAJGH": "541",
    "PIHHFELJLBC": "572",
    "HOJJIODKHPE": "592",
    "FKCBPEJLGCC": "2918",
    "ECPAMLMFHLJ": "2908",
    "JBDIFMONCAG": "2912",
    "GJGKKOGPPJC": "2905",
    "BCJFNBDODKB": "2922",
    "KMJGADGGHIH": "2907",
    "POFHGEBPHNP": "2920",
    "BCBNCBGIEJO": "2910",
    "GFGKHDBBKIL": "2916",
    "CFPNMMHIFLK": "2921",
    "AMPEPAJDMFH": "2909",
    "LPKHFHJDGOG": "2924",
    "GNENODIAGCE": "2911",
    "NBAOGEHPIAM": "5190",
    "CBFMJOHLCCD": "5196",
    "NDKAKLBNOPA": "5189",
    "JPFGDONNGEA": "5176",
    "PPNEGEHHFHC": "2390",
    "HHMLOCBABMC": "2396",
    "BEDOODLKBLH": "2389",
    "GKDNNONIJNJ": "2376",
    "BOHANKHMFEB": "2316",
    "MHKMFCNKEJI": "2356",
    "ABJCILGEAPG": "2334",
    "HNBLPFHLMEH": "2364",
    "GFLHBOHBNHI": "2400",
    "DMIMDAPMCMO": "2357",
    "KACHMOBDIJE": "2337",
    "KLNMFNNADPG": "2324",
    "JPKNOEMJICG": "2301",
    "MOPMEMHOLIK": "190",
    "OLEDCBIOIBM": "196",
    "CLFNBHKDFFH": "189",
    "DKIPBAAHKJM": "176",
    "CIJAANKJLEF": "116",
    "OPGJBDNICCH": "156",
    "BAFJOEPPPEA": "141",
    "GFFABHLMEIA": "172",
    "ILBLNLMHCPD": "192",
    "BEPBEGIBFIJ": "163",
    "PEAFHFCBPFF": "159",
    "PNDKKEIJPPN": "178",
    "NCFJLNGOJAD": "112",
    "BBDFLDLMAFA": "165",
    "BGHONDPPLBN": "199",
    "LMJAGHOBMLG": "175",
    "LMEHGMJBDFL": "146",
    "CECEPKGBFMG": "182",
    "AEIAGGMHFIO": "142",
    "LADACODDNGA": "194",
    "LGJJFJBCBIE": "177",
    "GBJPMDHMOGG": "186",
    "MIMCCLIKMIJ": "151",
    "IAHGJJDFDOI": "139",
    "OMENAAMNHAF": "195",
    "IMAKIKFJHOM": "150",
    "GJBLIANJAOC": "148",
    "CBANJHIMMBI": "198",
    "LHLIDAIOFCC": "197",
    "FMMBKMOPGDO": "181",
    "PEAPDEAMHHM": "170",
    "GNMHOBIGNDL": "135",
    "IHLADGBBKDA": "133",
    "NPAHEOCCAHH": "183",
    "KILNDKJNGBJ": "106",
    "MOJLFNMFKMH": "104",
    "JBKJMBEKPBB": "154",
    "DHCFHMOGOHP": "143",
    "DNLABMJAOMI": "129",
    "EMGCHDJIFIO": "128",
    "DEJJJOMGGIC": "174",
    "NCIMFDHIJIO": "173",
    "COFPPCENDKD": "188",
    "CJAOHLEJLDB": "149",
    "AKGLNBEFBAE": "118",
    "POECKGCEMFF": "158",
    "EGKFGNGJHKO": "115",
    "MJLAMJFMCHJ": "126",
    "OHLMKKDBBCL": "140",
    "LKDNGGNMDFE": "145",
    "AANJMLLAOLA": "134",
    "HIIDJCLGOLA": "164",
    "DLCLAJOMIKL": "200",
    "PCPAPFOEBPO": "157",
    "JDFJJBCDGEP": "137",
    "JKNNMPIHGJG": "124",
    "JEMHLKGAKCJ": "101",
    "IOFEFMEPAFP": "169",
    "FPPJFMKAMOK": "132",
    "BHLPANEFMHM": "119",
    "DEDIIKDDKEM": "127",
    "COCJKAPJLDM": "168",
    "PLLBADBHJJB": "193",
    "KDCFLLMGOAN": "152",
    "HBIGNFGKKDJ": "144",
    "PEMELLOACHH": "122",
    "MCGDLAKBJOC": "107",
    "AJKNMCDMLOI": "191",
    "IBGIEALDNPB": "147",
    "GFGCMBGAMGO": "136",
    "KPFDAAAHFOE": "138",
    "JBHPBCIOPOE": "160",
    "OPHFKHGDMBK": "180",
    "DLGHNNHLGEN": "153",
    "KAPPPLGDHBL": "105",
    "HOAAPIKFAMA": "109",
    "COLEEIFDJKE": "121",
    "FLHPFALHKNK": "114",
    "DLPNPDBPINP": "102",
    "LEIKEGJEGAP": "111",
    "IMAJBLHALDE": "117",
    "AONDAOGPHLJ": "120",
    "KMLMIEEPOFI": "185",
    "CJCKPFAEMNM": "131",
    "APBPLPHKKGC": "125",
    "MBBOODALGFB": "167",
    "MEAHPANFPHD": "179",
    "DNCELLIFEHB": "113",
    "GFCPGINLENH": "187",
    "LNLKHGPAEHB": "162",
    "GHMNCNNHLAI": "123",
    "DFPBHODHPKM": "130",
    "HMHLMKOOGFJ": "184",
    "BIJJHMLCFOF": "108",
    "AMLBFLIFIKP": "1290",
    "JAIDICBLKEP": "1296",
    "LLHOBJPHEPA": "1289",
    "NLBPIGMANAH": "1276",
    "CFPMGGHGBFL": "1216",
    "HLEGBPMAOGH": "1256",
    "CFFMDGNCJDD": "1241",
    "HMPNDBHLFPE": "1272",
    "BCGHJPEKLLD": "1292",
    "ECKONOENIGF": "1263",
    "LKOECLGEAJN": "1259",
    "MNBCEJBCJEH": "1278",
    "EEHKLPMFHGC": "490",
    "IMOKNCEDDIN": "496",
    "DCJBFMBMMHN": "489",
    "EJHEFMEOPDL": "476",
    "LJCDAMNBHJL": "416",
    "DNDFBIMEHCF": "456",
    "DABGGEPNIEP": "441",
    "ADBBIBDMOOB": "472",
    "DNJJKDAHJEL": "492",
    "PAADNAFBNIB": "463",
    "DEMEIIONLDG": "459",
    "ENMJALKLLJA": "478",
    "KDOLGMAIDIO": "412",
    "JKMGOFOBNBC": "475",
    "CBPKBCFKCKJ": "446",
    "OPNIFNNKOAI": "482",
    "GDOPKNJDFAL": "442",
    "EJJMNAGIMNB": "494",
    "PIINBBBJFHG": "477",
    "LNJDHHKEHBB": "486",
    "PAEHKJAIHFP": "451",
    "MHHNJNJOFIL": "439",
    "JFCJLKBKNFB": "495",
    "OMKNPDDIFNP": "450",
    "IONEPDGCMMG": "448",
    "CMPGGEKCDPC": "498",
    "FLOMGIAPBHG": "497",
    "ICLLOANFNEB": "481",
    "MMPFLFGLFFC": "470",
    "OKMLFKDCPMD": "435",
    "INOINOLAGLI": "433",
    "MFFLCFKINNA": "483",
    "BAGMJCABANG": "406",
    "CKJDCPDNGII": "404",
    "NLJFMCEGKPM": "454",
    "GEMCBFFADHJ": "443",
    "PFFEILDHDMB": "429",
    "NAMKFIIDGHA": "428",
    "MLOPPPIEEMH": "474",
    "NAONNMAPDMD": "473",
    "GKMEMGGPBCO": "488",
    "GGMODBOEOIL": "449",
    "LEFCJKGALNG": "418",
    "AGGOCPJOCCL": "458",
    "GFCGMHBPLHC": "415",
    "KMIHBBDHIFF": "426",
    "NNDLHKHDGJB": "440",
    "HOHKAJNDCIJ": "445",
    "EIGDCMPDAJO": "434",
    "LPENNMHPHGO": "464",
    "BMLLLCEODOK": "500",
    "KMIACMOIKNM": "457",
    "CHFGMLFKKAM": "437",
    "OAOLFJEABPH": "424",
    "DHBGNGAMFCK": "401",
    "AMMOLOMBCCH": "4109",
    "JPENDDDCINO": "4116",
    "IJCIIACAMHO": "4117",
    "FGEMJEBIEBF": "4149",
    "PEHFNKBDNNG": "4115",
    "NMJIDCKCBHG": "4126",
    "JDACOEJONKL": "4145",
    "KFPCHOEBPJN": "4122",
    "PGFAKNBIEFO": "4120",
    "KEPLBKGHMGK": "4123",
    "KFAMOPAFOHC": "6259",
    "DDLKOLJNFEB": "6266",
    "KGCAIOJAIEF": "6267",
    "HFOJLNAMPCI": "5609",
    "CDKILDCCGII": "5616",
    "MANPBEJLMKH": "5617",
    "FJEBBDBJPFG": "5649",
    "ENHECGKJAHP": "5615",
    "DEIEAFAHEDG": "5709",
    "LMMGPLEGNFE": "5716",
    "GNJDOGANMMF": "2890",
    "BEEJOACLJGF": "2896",
    "GOAICJCIDHN": "2889",
    "JEBBKCGCPPP": "2876",
    "AMJNBDMCMPH": "2816",
    "ABPHHHLKJBA": "2856",
    "LEIJECOECHD": "2841",
    "HJFNGMIHNON": "2872",
    "IMGADGHOCFK": "2892",
    "KGNPFFPBNJK": "2863",
    "PLDKKACDBPJ": "2859",
    "FJOEILNLMEC": "2878",
    "LKBDHDEIKGI": "2812",
    "EOOLFHCDEEA": "2865",
    "CFBEJOHNPIM": "2899",
    "BCEKJNJBPIP": "2875",
    "JANCDLBENLK": "5059",
    "HPMHCBAJHGA": "5066",
    "PMBNGFDIPJC": "5067",
    "EFPHCPGCPAI": "5099",
    "BKCFFEBAJBA": "5065",
    "NDLOBKKGODC": "5076",
    "IKCHHDPBHKO": "5095",
    "KPOICGBLJAH": "5072",
    "PLGBCAGCCPD": "5070",
    "OKJHIHCODGB": "5073",
    "KFHFIDANCLO": "5092",
    "JLAGKDFILIH": "5086",
    "GOIFNMPJFAL": "5081",
    "LLAHGFMLLBE": "5071",
    "HLJAMFHGDMO": "5100",
    "LPFPJCCBLKI": "5074",
    "CFNBMCMLMPE": "5075",
    "DMNBMHIFFHH": "5093",
    "PDJOLOBJOFI": "5087",
    "LLEACKJHOEG": "5098",
    "EOBKLFHDEBD": "5062",
    "AICCFCMGNBG": "5069",
    "FLECEKOBOLN": "5094",
    "PCHEDEBICFN": "3509",
    "MDMMFNOMJBO": "3516",
    "FKBFEKJHBHI": "3517",
    "NKEPKPDOHFG": "3549",
    "KKPPKDHGKJI": "3515",
    "PLEIKDOOEJB": "290",
    "IBPJMBKNICC": "296",
    "NBBBEMJDOMO": "289",
    "IOCPFMHFFFN": "276",
    "OLMNHDCCBOE": "216",
    "GIGOIBLMDHA": "256",
    "EBBFDEDKBNO": "241",
    "KELHGHLMPEG": "272",
    "DMMGIENKIKO": "292",
    "FCILOLPMHPE": "263",
    "PGDKDGKKGBF": "259",
    "HADOGPNKCLM": "278",
    "HCKDLDDBGEN": "212",
    "KAFMIMOBKKE": "265",
    "GKBGCPGCPAE": "299",
    "LIDLBFDMGHA": "275",
    "NAKEMMGEJBP": "246",
    "HIPLJNBHKLG": "282",
    "JDHNOBLAFGE": "242",
    "PGPHKCGFFIK": "294",
    "GCNOIGGCBBN": "277",
    "CLAIAONNJPO": "286",
    "LNAAFIHHCDN": "251",
    "GGMFJEKNFAC": "239",
    "ONKAKAHPGHO": "295",
    "JJIPJFEGDJG": "250",
    "PMHPGGKMPCJ": "248",
    "NMFKFALELHO": "298",
    "DLLJMBHCAPH": "297",
    "HGHBAOEAPNA": "281",
    "GCIGDCCBENG": "270",
    "AHMGLHBPOGH": "235",
    "NOOICDGONFO": "233",
    "IIIFOMLDNEC": "283",
    "OPNIBBJGIID": "206",
    "LPEIIGJFAGA": "204",
    "MAJEDICCBIL": "243",
    "FDBNHFALFHJ": "229",
    "OBPENFHAFGD": "228",
    "EMICDJCCFIP": "274",
    "FEPGLJNGIJF": "273",
    "CEBFJAOGLFB": "288",
    "BGJJBDDEOHG": "249",
    "LOJLNEMABDP": "218",
    "ALNJKBLPCHH": "258",
    "LHPLPIEOKGN": "215",
    "LOIPBNHAKOH": "226",
    "NCFPJNJGBGD": "240",
    "PICPLJMKJOB": "245",
    "JOLDFKPIFMF": "300",
    "OELCKILICIP": "257",
    "FMMDGBFOCNN": "237",
    "BLOKJGHICPI": "224",
    "FCLLABHADCK": "201",
    "MNDPKCGJAFF": "269",
    "COHGDKEIGAM": "232",
    "OMOJHMPFPPG": "219",
    "DCPCGJCCOJL": "227",
    "BGHKMPEDLJO": "268",
    "IGBFEJEONIE": "293",
    "AMDDNIGKMJG": "252",
    "ENKLEDNFFIC": "244",
    "KKHJMDINBOL": "222",
    "CDMLNNHBKIF": "207",
    "PDMODFFJAGA": "291",
    "FKPHLBHEAJA": "247",
    "NFFPIEIAODH": "236",
    "DCEEEDODLHB": "238",
    "GMGFBJCMMKD": "260",
    "HACFHECKHHB": "280",
    "MCBNOBMCOEH": "253",
    "ABCCOEDNBLH": "205",
    "AEDBACJCGMB": "209",
    "FBJNIGOFFBL": "221",
    "BDKHPEKDFCA": "214",
    "GOPJCGHFBNM": "202",
    "BCIIFHHBGJH": "211",
    "MLHGMKJPGMM": "217",
    "CMEINLHKMJA": "220",
    "MLIDIOPMEBK": "285",
    "EHDLDPHGGFF": "231",
    "HOKKMGGHCFD": "225",
    "NFFMBCKHDLJ": "267",
    "GKOJHPIPBHO": "279",
    "OKLAGFKPDJI": "213",
    "FLPNFCLHHNP": "287",
    "GMAEFKDKCLJ": "262",
    "CKMAPHDLBFJ": "223",
    "PINOHACCOJL": "230",
    "BJNCNJLGKKL": "284",
    "FHCIHKNPCKG": "208",
    "CBPCIBPLELE": "261",
    "NJODLDAMCNA": "210",
    "GOENHCJCPOL": "203",
    "BNAHADPMBIJ": "271",
    "LIGKGFEOAAL": "255",
    "LOFHHKFLEBM": "266",
    "FDEMGNEIOEH": "3357",
    "NFEMBPCMDLK": "3285",
    "FPKLJFJFMPI": "3090",
    "ALONGGGLLHP": "3338",
    "PJFGAPEJNGA": "3354",
    "DDECFGAEPFL": "3483",
    "NACCCJOAAGP": "3050",
    "PGNBFNNCAFB": "3363",
    "GLHFIFHNHGH": "3017",
    "KHLHDJADOMN": "3194",
    "CIFLDELJBNL": "3437",
    "NKAIGOMHPJB": "3479",
    "AHIJMECELNE": "3417",
    "EBEELCKAIEG": "3065",
    "LHGABNCEJMG": "3425",
    "AEOICKOILCK": "3103",
    "CJBOFJOHMON": "3019",
    "MEIOILGKCJC": "3332",
    "DJGPJPKMBDO": "3320",
    "CNOPGBHNGFB": "3241",
    "GBKPKCJPEAA": "3062",
    "BOIJKMNMIEH": "3261",
    "OAMKJPCABNC": "3443",
    "GMCOAPLLLOG": "3424",
    "EOCLBFJEPNJ": "3026",
    "FIJBHLMGIAN": "3281",
    "MEGNOIJENKI": "3467",
    "NEIGIGODCNL": "3333",
    "DPNNLLEHHCK": "3128",
    "JDJGBNOMMCP": "3168",
    "ELCOJDNMMDM": "3456",
    "IJAJCEENKHC": "3170",
    "PCCLMIBJNGN": "3234",
    "CDIJDIKAMLC": "3222",
    "AAEPEEBDGJB": "3008",
    "IKGNAMEPGKE": "3030",
    "FFOHPMNDCGA": "3335",
    "MKDGFMGJAEI": "3007",
    "LEBMIODJLOG": "3100",
    "LAMDJJOGEDA": "3353",
    "BKGBDCBDGKF": "3304",
    "IKHDMMGIPPN": "3289",
    "LCONNAKDFLI": "3307",
    "POINPIFINFH": "3057",
    "MKDKPGGPNHI": "3461",
    "CFIGKJKFEKO": "3454",
    "NNDJOINBKAB": "3231",
    "DMADALIOKGO": "3035",
    "OLNAKLCGDKD": "3138",
    "CDBHOOGAMEL": "3343",
    "FPPNHNKFNPK": "3060",
    "EPJBGCIPDEO": "3265",
    "LEHGOANEDOH": "3205",
    "HDJGNGLPHHO": "3207",
    "FGNKEMCGCCD": "3270",
    "DELAPOPINGI": "3382",
    "IEIOPBLDBDM": "3129",
    "MCCBOAPMOPB": "3273",
    "FDHEDLFKPHI": "3286",
    "PMPCHBJJJAN": "3018",
    "APABBPLFGOO": "3487",
    "BHEGBMEGACF": "3457",
    "LGLKPOAIEOP": "3145",
    "KDOMBPOPLDK": "3263",
    "NGMLGBCAPIA": "3496",
    "EDBBJDLNODE": "3327",
    "OACAFCNIOLD": "3497",
    "FPMKANGLGAP": "3198",
    "FKAFHNIHACL": "3139",
    "FHHIKGOMKPK": "3203",
    "PKBIBIIEKBM": "3246",
    "DIIBHMNKDJK": "3169",
    "CMOCHECCPBP": "3314",
    "HLHDHBEFNIJ": "3416",
    "AEIMANHHJAC": "3466",
    "BBAEFJPLEPN": "3408",
    "AODPOEJPGKM": "4440",
    "HPLHIFNNMEO": "4446",
    "BHCDLEGLAKB": "4439",
    "OABNMFAFFAI": "4426",
    "NKECGGDNBCB": "4366",
    "MDIJHFEDIGC": "4406",
    "APLBBCHALEL": "4391",
    "NGDHDKJNJAJ": "4422",
    "NIEBMAHPKCD": "4442",
    "AMNGHAEJJPL": "4413",
    "KOBNPJGDMAL": "4409",
    "MNKBGNBGOCE": "4428",
    "DAJCIMDMJBD": "4362",
    "DGJFEOAEIOF": "4415",
    "AEGNIMMJCEI": "4449",
    "OHALFGLLBHC": "4425",
    "HMKHCMNELAL": "9090",
    "ACJLEMECHMH": "790",
    "NFHPBKJDEMC": "796",
    "DPGDGHJEDFH": "789",
    "OLNLFCGNJMH": "776",
    "MFPLDKCEHKF": "716",
    "ANANDPPJAOD": "756",
    "BCGBHBAHONN": "741",
    "EPKOFNPJGBC": "772",
    "HFFEKJIIFDG": "792",
    "POILJBBMNCF": "763",
    "CNGMBOODNAC": "2590",
    "GIGMHHEFOPD": "2589",
    "FIBBCIGKLAA": "2576",
    "LHLPCMDFKPK": "2516",
    "BNHLBKBEKCN": "2556",
    "JKNNFNDEAOA": "2578",
    "JOFOPLGFKEJ": "2512",
    "JLPCIJCCNOI": "2565",
    "CLGOGGKLNHD": "2599",
    "NJIPJNNCPHD": "2575",
    "EIIEBEFANNG": "1090",
    "FKHLNMFAJBD": "1096",
    "FICNHFDNBKE": "1089",
    "ABCMGIEMGEP": "1076",
    "ALMFLAIFPCM": "1016",
    "HOLIILCCLHP": "1056",
    "OGKJAJFBMIO": "1041",
    "IMODKAICNHM": "1072",
    "MBFICLFHELI": "1092",
    "MNEMEFKMBCH": "1063",
    "KNHEBFKCDHB": "1059",
    "PPGGAIJGNKM": "1078",
    "NFAINKJCGNM": "1012",
    "IHFNGMCDILI": "1065",
    "FHFLCAHNFCP": "1099",
    "ODLKDIPGMOC": "1075",
    "IINMOIBOOAB": "1046",
    "FBCEBBAFBDJ": "4090",
    "MEEFPHGBHDK": "4096",
    "GJMBMJPBHPH": "4016",
    "HIKJADDBLEJ": "4056",
    "KJKEOIMDAKE": "4041",
    "KOFDKPBCFJE": "4072",
    "DKBIHCALLNK": "4092",
    "JKGBNOFHLLC": "4063",
    "DNNCFLDIPFG": "4059",
    "KDJMJHKMJJM": "4078",
    "IEMEICMDIIM": "4012",
    "JGHMHJOEDHB": "4065",
    "CJPAMGBJCHG": "4099",
    "OCCAFEBEKAD": "4075",
    "BFDHKNPNICA": "4046",
    "MBKMBEIOGGC": "4082",
    "CAFFCEFAALD": "4042",
    "HNGNCNLBPEF": "4094",
    "MECIFMHPFCN": "4077",
    "CDMDKCDGNPE": "4086",
    "LFHFMBJIGJO": "4051",
    "EHLMHBGMEKC": "4039",
    "LNGOAPEFMHH": "4095",
    "PGPJPNEGENN": "4050",
    "DGEDGFBGJFI": "4048",
    "CNDDJJBFEBN": "4098",
    "HPPMHJGCJDO": "4097",
    "CMCLJJPIFEO": "4081",
    "OCKILEPOHNF": "4070",
    "DMEMJACJNFO": "4035",
    "JKFNDBHLDAE": "4033",
    "CDJIDKDAIDP": "4083",
    "LCOBIMJLBLE": "4006",
    "NHHIFPNDDJG": "4004",
    "IJLJNBINDBI": "4054",
    "DONBHCNMFJN": "4043",
    "MIDNPIGENEB": "4029",
    "FCACOLLBEIL": "4028",
    "PHAHKLANPKO": "4074",
    "KMMICFCAEMN": "4073",
    "ECLPOFDBAGI": "4088",
    "NHDBOLOEILO": "4049",
    "PJGONDKJIHI": "4018",
    "GDGFCOGCFGI": "4058",
    "CFPHGJPKKHP": "4015",
    "MAIBFBAOOEK": "4026",
    "DIECLABFMCB": "4040",
    "GFHNELKHBCP": "4045",
    "GGINOEODDHC": "4034",
    "PPLMPOEMAAO": "4064",
    "GFDDMIJMCEJ": "4100",
    "OHOAMNEBEDD": "4057",
    "HOJEGAPGGNE": "4037",
    "FCLOOKLKLCE": "4024",
    "BGKPCOACAPN": "4001",
    "HENMGNPHEAB": "4069",
    "ELFBKLJGGFD": "4032",
    "JNHHBEBKNFO": "4019",
    "CLEOEMBHLBK": "4027",
    "MPMEMEBCIAG": "4068",
    "LOPIDIHJEBH": "4093",
    "CGLGMNLOFPD": "4052",
    "HMPANOFIBOG": "4044",
    "NJMAALJHAOF": "4022",
    "MNPEELCICCC": "4007",
    "FCGCFDIECGI": "4091",
    "FONPLIJKICI": "4047",
    "GKNAAPMLMBM": "4036",
    "FFHJPNCHNMD": "4038",
    "GJIPCNAOBPA": "6190",
    "BLMEIMMKNIG": "6196",
    "BFAMJMJHDHO": "6189",
    "DOJPPHABLKD": "6176",
    "EHMINELAAPN": "6116",
    "HINNHENMOBF": "6156",
    "KIMFNJJNOAE": "6141",
    "CJJFIHPLEMJ": "6172",
    "PLFOMMBGEIF": "6192",
    "AOEDIDDNEHH": "6163",
    "DIJAILOHJEA": "6159",
    "DOOOMKLOHOB": "2490",
    "ONJNAGDHCDM": "2496",
    "DNLLHGCKDOC": "2489",
    "PPJMEAOLGHN": "2476",
    "KJFKGBBOLFJ": "2456",
    "EBBOIDCGABB": "2441",
    "BHBFGMDJLLI": "2472",
    "MPFPLNBLIKB": "2492",
    "PBGNHCLPLIN": "2459",
    "PDANKGGIHNG": "2478",
    "ODPFOIJMMMP": "2412",
    "GPCHOKFJKHO": "2465",
    "JGPBPDJJAJO": "2477",
    "APPKEMOBLIB": "2486",
    "LPOJOJCHIMJ": "2451",
    "LFAECKJPJFB": "2439",
    "KGDJCGBBNBK": "2481",
    "IPFDOCCCPNL": "2470",
    "LHDCNOCCOPF": "2435",
    "CKKELCJKDDB": "2433",
    "BCKCLMPIOGE": "2483",
    "KLFKKLCPDKL": "6309",
    "BNBJPDOPPCC": "6316",
    "KJMGOCCECKI": "6317",
    "NICLPBFFHAA": "6349",
    "GAGHHOCGHKD": "6345",
    "HMPGIICKHMD": "6322",
    "EGFDJDEEIPJ": "6320",
    "AHFCMBIONFL": "6323",
    "FALNIBLGNCF": "6342",
    "OBIOHADBMBC": "6336",
    "OKAPOMMIKFD": "6331",
    "BFCKNLNKAOD": "6321",
    "AHIDOJBDLOF": "6350",
    "HIDEKBNDDIP": "6324",
    "AAEIMMOLJAF": "6325",
    "AJFBMFBKOIG": "6343",
    "BFMJGJJOHPC": "2290",
    "AGMEBNFLEPJ": "2296",
    "IAOFCGMOHPH": "2289",
    "NCPPBEPJKGI": "2276",
    "OLIPECANKPG": "2216",
    "GJPHFPEDDIM": "2277",
    "PPKBEMFOPPL": "2286",
    "HHHOIHFIJDN": "2251",
    "OONPHCCDMBF": "2239",
    "KIPKHNIMECI": "2295",
    "FDNOEEEKJKP": "2250",
    "CMPCAGNBCLB": "4259",
    "GOHHKGPBDKF": "4299",
    "NIKHJHHKIMC": "4265",
    "NEEIJAKMAFF": "4272",
    "KGFNKABPJMB": "4270",
    "KPHPHAEKPDO": "4273",
    "JDNIONAJAPG": "4292",
    "ABEOGNPCKPI": "4286",
    "JIHGKNPOAND": "4281",
    "GHCKNNAIEKO": "4271",
    "EHFMCONIKJH": "4300",
    "EELHHAMJFEH": "4274",
    "DKBDMKJOAFM": "4275",
    "KIJGGFINIBP": "4262",
    "NAPDGILJNIK": "4251",
    "HDJLOAEAPLC": "4296",
    "OGAHAOPHMIM": "4257",
    "HCMHNCMNKIN": "4258",
    "FHLAOOICHDH": "4291",
    "KOINNJPEKPI": "4263",
    "JLFMKPEFCDL": "4261",
    "HGDJMCEDNKB": "4290",
    "GBNDIEALIGJ": "4284",
    "PJPIJGLENEK": "4256",
    "EBEGNJPHGMG": "4288",
    "DGNBGJPCNAN": "4278",
    "KBMBACOLNMM": "4260",
    "NBCPOJPGAOA": "4254",
    "PBKOFJACIMK": "4279",
    "GOGACGCLFFK": "4255",
    "LDDBEADHCDI": "4252",
    "JNINDOJAJMB": "4285",
    "OFGALPKIKGN": "4277",
    "OLGGNMNDPHD": "6051",
    "NDPCABCJAPA": "5944",
    "MKAEFCBHBFO": "5902",
    "DDKCAPKPPNI": "6082",
    "HAMCKHKPGKG": "6065",
    "AMCLCEJGJNF": "6022",
    "CPENMHPGPLO": "6086",
    "JAPKAKGMJKK": "5949",
    "INFKPPMCMFH": "6060",
    "FLLAOOKCCHL": "5986",
    "DAEAOLEIKOA": "6008",
    "BLDIPLHJBMK": "5947",
    "MIAOMBLILNG": "6035",
    "NJIKLIJCLDA": "6089"
}